monotone_bipartition/__init__.py
monotone_bipartition/bipartition.py
monotone_bipartition/draw.py
monotone_bipartition/hausdorff.py
monotone_bipartition/rectangles.py
monotone_bipartition/refine.py
monotone_bipartition/search.py
monotone_bipartition/test_bipartition.py
monotone_bipartition/test_hausdorff.py
monotone_bipartition/test_project.py
monotone_bipartition/test_rectangles.py
monotone_bipartition/test_refine.py
monotone_bipartition/utils.py
monotone_bipartition-stubs/monotone_bipartition.pyi
monotone_bipartition-stubs/monotone_hausdorff.pyi
monotone_bipartition-stubs/monotone_rectangles.pyi
monotone_bipartition-0.3.1.dist-info/LICENSE
monotone_bipartition-0.3.1.dist-info/WHEEL
monotone_bipartition-0.3.1.dist-info/METADATA
monotone_bipartition-0.3.1.dist-info/RECORD
